wsdatautil/__init__.py
wsdatautil/_wsframecoder.c
wsdatautil/_wsframecoder.pyi
wsdatautil/py.typed
wsdatautil-1.1.dist-info/LICENSE
wsdatautil-1.1.dist-info/METADATA
wsdatautil-1.1.dist-info/WHEEL
wsdatautil-1.1.dist-info/top_level.txt
wsdatautil-1.1.dist-info/RECORD
