Metadata-Version: 2.1
Name: wsdatautil
Version: 1.1
Summary: The WsDataUtil is a lightweight, highly compatible Python module to process WebSocket data.
Author-email: "Adrian F. Hoefflin" <srccircumflex@outlook.com>
License: MIT
Project-URL: Homepage, https://github.com/srccircumflex/wsdatautil
Keywords: ws,wss,websocket,websocket protocol,python c extension,websocket encode,websocket parser,websocket frame parser,websocket frame
Classifier: Environment :: Web Environment
Classifier: Intended Audience :: Developers
Classifier: Programming Language :: Python :: 3
Classifier: Programming Language :: C
Requires-Python: >=3.9
License-File: LICENSE
